ml4math/__about__.py
ml4math/__init__.py
ml4math/datasets/__init__.py
ml4math/datasets/config.py
ml4math/datasets/minif2f.py
ml4math-0.0.1.dist-info/METADATA
ml4math-0.0.1.dist-info/WHEEL
ml4math-0.0.1.dist-info/licenses/LICENSE.txt
ml4math-0.0.1.dist-info/RECORD
